{
  "took" : 11,
  "timed_out" : false,
  "_shards" : {
    "total" : 5,
    "successful" : 5,
    "skipped" : 0,
    "failed" : 0
  },
  "hits" : {
    "total" : 7243,
    "max_score" : 0.0,
    "hits" : [ ]
  },
  "aggregations" : {"sign_date" : {"buckets" : [
        {
          "key" : "同期",
          "from" : 1.6172352E12,
          "from_as_string" : "2021-04-01 00:00:00",
          "to" : 1.6224192E12,
          "to_as_string" : "2021-05-31 00:00:00",
          "doc_count" : 234,
          "brm_department" : {
            "doc_count_error_upper_bound" : 0,
            "sum_other_doc_count" : 0,
            "buckets" : [
              {
                "key" : "成都区,成都区大客户一部",
                "doc_count" : 121,
                "newoldtype" : {
                  "doc_count_error_upper_bound" : 0,
                  "sum_other_doc_count" : 0,
                  "buckets" : [
                    {
                      "key" : "新项目",
                      "doc_count" : 69,
                      "sign_money" : {
                        "value" : 3697337.0
                      },
                      "sign_project_id" : {
                        "value" : 69
                      }
                    },
                    {
                      "key" : "老项目",
                      "doc_count" : 52,
                      "sign_money" : {
                        "value" : 1.1302163E7
                      },
                      "sign_project_id" : {
                        "value" : 52
                      }
                    }
                  ]
                },
                "sign_money" : {
                  "value" : 1.49995E7
                },
                "sign_project_id" : {
                  "value" : 121
                }
              },
              {
                "key" : "成都区,成都区银行部",
                "doc_count" : 37,
                "newoldtype" : {
                  "doc_count_error_upper_bound" : 0,
                  "sum_other_doc_count" : 0,
                  "buckets" : [
                    {
                      "key" : "新项目",
                      "doc_count" : 19,
                      "sign_money" : {
                        "value" : 1710910.0
                      },
                      "sign_project_id" : {
                        "value" : 19
                      }
                    },
                    {
                      "key" : "老项目",
                      "doc_count" : 18,
                      "sign_money" : {
                        "value" : 2221334.0
                      },
                      "sign_project_id" : {
                        "value" : 18
                      }
                    }
                  ]
                },
                "sign_money" : {
                  "value" : 3932244.0
                },
                "sign_project_id" : {
                  "value" : 37
                }
              },
              {
                "key" : "成都区,成都区渠道部",
                "doc_count" : 29,
                "newoldtype" : {
                  "doc_count_error_upper_bound" : 0,
                  "sum_other_doc_count" : 0,
                  "buckets" : [
                    {
                      "key" : "新项目",
                      "doc_count" : 17,
                      "sign_money" : {
                        "value" : 1547634.0
                      },
                      "sign_project_id" : {
                        "value" : 17
                      }
                    },
                    {
                      "key" : "老项目",
                      "doc_count" : 12,
                      "sign_money" : {
                        "value" : 1506054.0
                      },
                      "sign_project_id" : {
                        "value" : 12
                      }
                    }
                  ]
                },
                "sign_money" : {
                  "value" : 3053688.0
                },
                "sign_project_id" : {
                  "value" : 29
                }
              },
              {
                "key" : "成都区,成都区保险部",
                "doc_count" : 27,
                "newoldtype" : {
                  "doc_count_error_upper_bound" : 0,
                  "sum_other_doc_count" : 0,
                  "buckets" : [
                    {
                      "key" : "新项目",
                      "doc_count" : 15,
                      "sign_money" : {
                        "value" : 548333.0
                      },
                      "sign_project_id" : {
                        "value" : 15
                      }
                    },
                    {
                      "key" : "老项目",
                      "doc_count" : 12,
                      "sign_money" : {
                        "value" : 684379.0
                      },
                      "sign_project_id" : {
                        "value" : 12
                      }
                    }
                  ]
                },
                "sign_money" : {
                  "value" : 1232712.0
                },
                "sign_project_id" : {
                  "value" : 27
                }
              },
              {
                "key" : "成都区,成都区分院",
                "doc_count" : 19,
                "newoldtype" : {
                  "doc_count_error_upper_bound" : 0,
                  "sum_other_doc_count" : 0,
                  "buckets" : [
                    {
                      "key" : "新项目",
                      "doc_count" : 17,
                      "sign_money" : {
                        "value" : 522247.0966796875
                      },
                      "sign_project_id" : {
                        "value" : 17
                      }
                    },
                    {
                      "key" : "老项目",
                      "doc_count" : 2,
                      "sign_money" : {
                        "value" : 30019.0
                      },
                      "sign_project_id" : {
                        "value" : 2
                      }
                    }
                  ]
                },
                "sign_money" : {
                  "value" : 552266.0966796875
                },
                "sign_project_id" : {
                  "value" : 19
                }
              },
              {
                "key" : "成都区,成都区离职人员",
                "doc_count" : 1,
                "newoldtype" : {
                  "doc_count_error_upper_bound" : 0,
                  "sum_other_doc_count" : 0,
                  "buckets" : [
                    {
                      "key" : "新项目",
                      "doc_count" : 1,
                      "sign_money" : {
                        "value" : 3000.0
                      },
                      "sign_project_id" : {
                        "value" : 1
                      }
                    }
                  ]
                },
                "sign_money" : {
                  "value" : 3000.0
                },
                "sign_project_id" : {
                  "value" : 1
                }
              }
            ]
          }
        },
        {
          "key" : "当期",
          "from" : 1.6487712E12,
          "from_as_string" : "2022-04-01 00:00:00",
          "to" : 1.6539552E12,
          "to_as_string" : "2022-05-31 00:00:00",
          "doc_count" : 209,
          "brm_department" : {
            "doc_count_error_upper_bound" : 0,
            "sum_other_doc_count" : 0,
            "buckets" : [
              {
                "key" : "成都区,成都区大客户一部",
                "doc_count" : 85,
                "newoldtype" : {
                  "doc_count_error_upper_bound" : 0,
                  "sum_other_doc_count" : 0,
                  "buckets" : [
                    {
                      "key" : "老项目",
                      "doc_count" : 58,
                      "sign_money" : {
                        "value" : 1.7408563E7
                      },
                      "sign_project_id" : {
                        "value" : 58
                      }
                    },
                    {
                      "key" : "新项目",
                      "doc_count" : 27,
                      "sign_money" : {
                        "value" : 3808703.0
                      },
                      "sign_project_id" : {
                        "value" : 27
                      }
                    }
                  ]
                },
                "sign_money" : {
                  "value" : 2.1217266E7
                },
                "sign_project_id" : {
                  "value" : 85
                }
              },
              {
                "key" : "成都区,成都区银行部",
                "doc_count" : 44,
                "newoldtype" : {
                  "doc_count_error_upper_bound" : 0,
                  "sum_other_doc_count" : 0,
                  "buckets" : [
                    {
                      "key" : "老项目",
                      "doc_count" : 33,
                      "sign_money" : {
                        "value" : 4559764.59375
                      },
                      "sign_project_id" : {
                        "value" : 33
                      }
                    },
                    {
                      "key" : "新项目",
                      "doc_count" : 11,
                      "sign_money" : {
                        "value" : 2573558.0
                      },
                      "sign_project_id" : {
                        "value" : 11
                      }
                    }
                  ]
                },
                "sign_money" : {
                  "value" : 7133322.59375
                },
                "sign_project_id" : {
                  "value" : 44
                }
              },
              {
                "key" : "成都区,成都区保险部",
                "doc_count" : 29,
                "newoldtype" : {
                  "doc_count_error_upper_bound" : 0,
                  "sum_other_doc_count" : 0,
                  "buckets" : [
                    {
                      "key" : "老项目",
                      "doc_count" : 15,
                      "sign_money" : {
                        "value" : 3083739.546875
                      },
                      "sign_project_id" : {
                        "value" : 15
                      }
                    },
                    {
                      "key" : "新项目",
                      "doc_count" : 14,
                      "sign_money" : {
                        "value" : 1483516.08984375
                      },
                      "sign_project_id" : {
                        "value" : 14
                      }
                    }
                  ]
                },
                "sign_money" : {
                  "value" : 4567255.63671875
                },
                "sign_project_id" : {
                  "value" : 29
                }
              },
              {
                "key" : "成都区,成都区渠道部",
                "doc_count" : 27,
                "newoldtype" : {
                  "doc_count_error_upper_bound" : 0,
                  "sum_other_doc_count" : 0,
                  "buckets" : [
                    {
                      "key" : "老项目",
                      "doc_count" : 17,
                      "sign_money" : {
                        "value" : 4749420.0
                      },
                      "sign_project_id" : {
                        "value" : 17
                      }
                    },
                    {
                      "key" : "新项目",
                      "doc_count" : 10,
                      "sign_money" : {
                        "value" : 1318706.0
                      },
                      "sign_project_id" : {
                        "value" : 10
                      }
                    }
                  ]
                },
                "sign_money" : {
                  "value" : 6068126.0
                },
                "sign_project_id" : {
                  "value" : 27
                }
              },
              {
                "key" : "成都区,成都区分院",
                "doc_count" : 24,
                "newoldtype" : {
                  "doc_count_error_upper_bound" : 0,
                  "sum_other_doc_count" : 0,
                  "buckets" : [
                    {
                      "key" : "新项目",
                      "doc_count" : 14,
                      "sign_money" : {
                        "value" : 170961.0
                      },
                      "sign_project_id" : {
                        "value" : 14
                      }
                    },
                    {
                      "key" : "老项目",
                      "doc_count" : 10,
                      "sign_money" : {
                        "value" : 954658.0
                      },
                      "sign_project_id" : {
                        "value" : 10
                      }
                    }
                  ]
                },
                "sign_money" : {
                  "value" : 1125619.0
                },
                "sign_project_id" : {
                  "value" : 24
                }
              }
            ]
          }
        }
      ]
    }
  }
}